{"name":"Validar que permita depositar mediante tarjeta con el monto máximo","id":"poder-generar-el-código-de-depósito;validar-que-permita-depositar-mediante-tarjeta-con-el-monto-máximo","scenarioId":"DepositoTarjeta:Validar que permita depositar mediante tarjeta con el monto máximo","methodName":"Validar que permita depositar mediante tarjeta con el monto máximo","testSteps":[{"number":1,"description":"1: Validar que permita depositar mediante tarjeta con el monto máximo ({Vertical\u003dIr a casino, Pasarela\u003dDebitoCredito, Tarjeta\u003d4009175332806176, Fechacaducidad\u003d11/25, CVV\u003d123})","duration":37922,"startTime":"2024-02-19T19:29:50.433408600-05:00[America/Lima]","precondition":false,"level":0,"lineNumber":26,"children":[{"number":2,"description":"Given realizo el inicio de sesión con un usuario en moneda soles sin depósitos","duration":7659,"startTime":"2024-02-19T19:29:50.474076-05:00[America/Lima]","screenshots":[{"screenshot":"2634562a9c1f449d441e81a2bc070058f481d1d800fc02c26fd0208b62478793.png","htmlSource":"pagesource9330910671472456668.html","timeStamp":1708388997955,"screenshotName":"2634562a9c1f449d441e81a2bc070058f481d1d800fc02c26fd0208b62478793.png"}],"result":"SUCCESS","precondition":false,"level":1,"children":[{"number":3,"description":"Abrir pagina principal","duration":5054,"startTime":"2024-02-19T19:29:50.971028900-05:00[America/Lima]","screenshots":[{"screenshot":"6d8e379713361fd1a027e1b4cd2b1c672a452f049a4b5edbbf22e1f4e0cfd3cd.png","htmlSource":"pagesource7393830946876757711.html","timeStamp":1708388996021,"screenshotName":"6d8e379713361fd1a027e1b4cd2b1c672a452f049a4b5edbbf22e1f4e0cfd3cd.png"}],"result":"SUCCESS","precondition":false,"level":2}]},{"number":4,"description":"When Me encuentro en \"Ir a casino\"","duration":5619,"startTime":"2024-02-19T19:29:58.136557800-05:00[America/Lima]","result":"SUCCESS","precondition":false,"level":1},{"number":5,"description":"And ingreso los datos del usuario\r\n| usuario | contrasenna |\r\n| usuVahpc | atl1Vipeh |","duration":2020,"startTime":"2024-02-19T19:30:03.756897200-05:00[America/Lima]","screenshots":[{"screenshot":"23d884a01dbfef02cbd06fe1e6b1b12deaf6d2b4539f9d0bcfcb4c1f9c005ccb.png","htmlSource":"pagesource18133869646089523666.html","timeStamp":1708389005771,"screenshotName":"23d884a01dbfef02cbd06fe1e6b1b12deaf6d2b4539f9d0bcfcb4c1f9c005ccb.png"}],"result":"SUCCESS","precondition":false,"level":1},{"number":6,"description":"And Selecciono botón Depositar\"","duration":472,"startTime":"2024-02-19T19:30:05.782644200-05:00[America/Lima]","screenshots":[{"screenshot":"f3a817a7e99e7604135769ed8f93a4c07f45cf513222d4827fb7633fa26439aa.png","htmlSource":"pagesource15924104047194991775.html","timeStamp":1708389006252,"screenshotName":"f3a817a7e99e7604135769ed8f93a4c07f45cf513222d4827fb7633fa26439aa.png"}],"result":"SUCCESS","precondition":false,"level":1},{"number":7,"description":"And Selecciono \"DebitoCredito\"","duration":5008,"startTime":"2024-02-19T19:30:06.256836600-05:00[America/Lima]","screenshots":[{"screenshot":"2ee2aa67ea4976bf24b52b76bf8f44bdda92a872e2e9b97950ee1f2c67e3dfe8.png","htmlSource":"pagesource17170840772720121870.html","timeStamp":1708389011263,"screenshotName":"2ee2aa67ea4976bf24b52b76bf8f44bdda92a872e2e9b97950ee1f2c67e3dfe8.png"}],"result":"SUCCESS","precondition":false,"level":1},{"number":8,"description":"And Selecciono el monto:\r\n| MontoOrigen |\r\n| 300 |","duration":437,"startTime":"2024-02-19T19:30:11.267386600-05:00[America/Lima]","screenshots":[{"screenshot":"e5a637cc4bebee05f8a7e6e728aae1caa344830cdbc350dd5751c130cf5ca5b0.png","htmlSource":"pagesource2006357976080769756.html","timeStamp":1708389011699,"screenshotName":"e5a637cc4bebee05f8a7e6e728aae1caa344830cdbc350dd5751c130cf5ca5b0.png"}],"result":"SUCCESS","precondition":false,"level":1},{"number":9,"description":"And Acepto términos y condiciones de depósito","duration":15094,"startTime":"2024-02-19T19:30:11.707166-05:00[America/Lima]","result":"SUCCESS","precondition":false,"level":1},{"number":10,"description":"And Selecciono botón Siguiente tarjeta","duration":1548,"startTime":"2024-02-19T19:30:26.806000300-05:00[America/Lima]","result":"ERROR","precondition":false,"level":1,"lineNumber":26,"children":[{"number":11,"description":"Seleccionar boton deposito siguiente","duration":347,"startTime":"2024-02-19T19:30:27.944369300-05:00[America/Lima]","screenshots":[{"screenshot":"c2bbe98c59e360a1e218a728051defcd41b53910662cb9dd1218a2a109ed06e9.png","htmlSource":"pagesource11841866024261459645.html","timeStamp":1708389028285,"screenshotName":"c2bbe98c59e360a1e218a728051defcd41b53910662cb9dd1218a2a109ed06e9.png"}],"exception":{"errorType":"org.openqa.selenium.ElementClickInterceptedException","message":"element click intercepted: Element \u003cbutton id\u003d\"depositButton\" class\u003d\"jsx-bbc0a237ca44e34d clmc-btn-primary clmc-disabled\"\u003e...\u003c/button\u003e is not clickable at point (768, 607). Other element would receive the click: \u003cdiv class\u003d\"jsx-bbc0a237ca44e34d clmc-flex-center containerBtnPasarelaFlex\"\u003e...\u003c/div\u003e\n  (Session info: chrome\u003d121.0.6167.185)\nBuild info: version: \u00274.12.0\u0027, revision: \u0027249f2a7d1b*\u0027\nSystem info: os.name: \u0027Windows 10\u0027, os.arch: \u0027amd64\u0027, os.version: \u002710.0\u0027, java.version: \u002721.0.1\u0027\nDriver info: org.openqa.selenium.chrome.ChromeDriver\nCommand: [b02882735822dd6505d810ed308f9b91, clickElement {id\u003dB78C1B15E8C088EC93786EAE31AF9569_element_163}]\nCapabilities {acceptInsecureCerts: false, browserName: chrome, browserVersion: 121.0.6167.185, chrome: {chromedriverVersion: 121.0.6167.184 (057a8ae7deb..., userDataDir: C:\\Users\\RCARRA~1\\AppData\\L...}, fedcm:accounts: true, goog:chromeOptions: {debuggerAddress: localhost:55821}, networkConnectionEnabled: false, pageLoadStrategy: normal, platformName: windows, proxy: Proxy(), se:cdp: ws://localhost:55821/devtoo..., se:cdpVersion: 121.0.6167.185, setWindowRect: true, strictFileInteractability: false, timeouts: {implicit: 0, pageLoad: 300000, script: 30000}, unhandledPromptBehavior: dismiss and notify, webauthn:extension:credBlob: true, webauthn:extension:largeBlob: true, webauthn:extension:minPinLength: true, webauthn:extension:prf: true, webauthn:virtualAuthenticators: true}\nElement: [[ChromeDriver: chrome on windows (b02882735822dd6505d810ed308f9b91)] -\u003e xpath: //button[@id\u003d\u0027depositButton\u0027]]\nSession ID: b02882735822dd6505d810ed308f9b91","stackTrace":[{"declaringClass":"atlantic.main.util.PageObjectUtil","methodName":"seleniumClick","fileName":"PageObjectUtil.java","lineNumber":63},{"declaringClass":"atlantic.main.page.PageDeposito","methodName":"seleccionarBotonDepositoSiguiente","fileName":"PageDeposito.java","lineNumber":66},{"declaringClass":"net.thucydides.core.steps.BaseMethodRunner","methodName":"invokeMethod","fileName":"BaseMethodRunner.java","lineNumber":18},{"declaringClass":"net.thucydides.core.steps.NormalMethodRunner","methodName":"invokeMethodAndNotifyFailures","fileName":"NormalMethodRunner.java","lineNumber":18},{"declaringClass":"net.thucydides.core.steps.StepInterceptor","methodName":"runNormalMethod","fileName":"StepInterceptor.java","lineNumber":420},{"declaringClass":"net.thucydides.core.steps.StepInterceptor","methodName":"testStepResult","fileName":"StepInterceptor.java","lineNumber":195},{"declaringClass":"net.thucydides.core.steps.StepInterceptor","methodName":"intercept","fileName":"StepInterceptor.java","lineNumber":92},{"declaringClass":"atlantic.main.step.StepDeposito","methodName":"seleccionarDepositoSiguiente","fileName":"StepDeposito.java","lineNumber":23},{"declaringClass":"net.thucydides.core.steps.BaseMethodRunner","methodName":"invokeMethod","fileName":"BaseMethodRunner.java","lineNumber":18},{"declaringClass":"net.thucydides.core.steps.NormalMethodRunner","methodName":"invokeMethodAndNotifyFailures","fileName":"NormalMethodRunner.java","lineNumber":18},{"declaringClass":"net.thucydides.core.steps.StepInterceptor","methodName":"runNormalMethod","fileName":"StepInterceptor.java","lineNumber":420},{"declaringClass":"net.thucydides.core.steps.StepInterceptor","methodName":"testStepResult","fileName":"StepInterceptor.java","lineNumber":195},{"declaringClass":"net.thucydides.core.steps.StepInterceptor","methodName":"intercept","fileName":"StepInterceptor.java","lineNumber":92},{"declaringClass":"com.atlantic.test.definition.DefDepositoTarjeta","methodName":"selecciono_botón_siguiente_tarjeta","fileName":"DefDepositoTarjeta.java","lineNumber":32},{"declaringClass":"io.cucumber.java.Invoker","methodName":"doInvoke","fileName":"Invoker.java","lineNumber":66},{"declaringClass":"io.cucumber.java.Invoker","methodName":"invoke","fileName":"Invoker.java","lineNumber":24},{"declaringClass":"io.cucumber.java.AbstractGlueDefinition","methodName":"invokeMethod","fileName":"AbstractGlueDefinition.java","lineNumber":47},{"declaringClass":"io.cucumber.java.JavaStepDefinition","methodName":"execute","fileName":"JavaStepDefinition.java","lineNumber":29},{"declaringClass":"io.cucumber.core.runner.CoreStepDefinition","methodName":"execute","fileName":"CoreStepDefinition.java","lineNumber":66},{"declaringClass":"io.cucumber.core.runner.PickleStepDefinitionMatch","methodName":"runStep","fileName":"PickleStepDefinitionMatch.java","lineNumber":63},{"declaringClass":"io.cucumber.core.runner.TestStep","methodName":"executeStep","fileName":"TestStep.java","lineNumber":84},{"declaringClass":"io.cucumber.core.runner.TestStep","methodName":"run","fileName":"TestStep.java","lineNumber":56},{"declaringClass":"io.cucumber.core.runner.PickleStepTestStep","methodName":"run","fileName":"PickleStepTestStep.java","lineNumber":51},{"declaringClass":"io.cucumber.core.runner.TestCase","methodName":"run","fileName":"TestCase.java","lineNumber":84},{"declaringClass":"io.cucumber.core.runner.Runner","methodName":"runPickle","fileName":"Runner.java","lineNumber":75},{"declaringClass":"io.cucumber.core.runtime.CucumberExecutionContext","methodName":"lambda$runTestCase$5","fileName":"CucumberExecutionContext.java","lineNumber":137},{"declaringClass":"io.cucumber.core.runtime.RethrowingThrowableCollector","methodName":"executeAndThrow","fileName":"RethrowingThrowableCollector.java","lineNumber":23},{"declaringClass":"io.cucumber.core.runtime.CucumberExecutionContext","methodName":"runTestCase","fileName":"CucumberExecutionContext.java","lineNumber":137},{"declaringClass":"io.cucumber.junit.FeatureRunner","methodName":"runChild","fileName":"FeatureRunner.java","lineNumber":144},{"declaringClass":"io.cucumber.junit.FeatureRunner","methodName":"runChild","fileName":"FeatureRunner.java","lineNumber":28},{"declaringClass":"io.cucumber.junit.FeatureRunner","methodName":"run","fileName":"FeatureRunner.java","lineNumber":137},{"declaringClass":"io.cucumber.junit.CucumberSerenityBaseRunner","methodName":"runChild","fileName":"CucumberSerenityBaseRunner.java","lineNumber":330},{"declaringClass":"io.cucumber.junit.CucumberSerenityBaseRunner","methodName":"runChild","fileName":"CucumberSerenityBaseRunner.java","lineNumber":51},{"declaringClass":"com.atlantic.test.runner.RunPersonalizar","methodName":"run","fileName":"RunPersonalizar.java","lineNumber":36}]},"result":"ERROR","precondition":false,"level":2},{"number":12,"description":"Seleccionar deposito siguiente","duration":2,"startTime":"2024-02-19T19:30:28.291882300-05:00[America/Lima]","result":"ERROR","precondition":false,"level":2},{"number":13,"description":"And Selecciono boton Pagar sin agregar tarjeta","duration":9,"startTime":"2024-02-19T19:30:28.308581600-05:00[America/Lima]","result":"SKIPPED","precondition":false,"level":2},{"number":14,"description":"And Ingreso \"4009175332806176\" \"11/25\" Ingreso \"123\"","duration":4,"startTime":"2024-02-19T19:30:28.318635200-05:00[America/Lima]","result":"SKIPPED","precondition":false,"level":2},{"number":15,"description":"And Selcciono botón Depositar","duration":3,"startTime":"2024-02-19T19:30:28.323635100-05:00[America/Lima]","result":"SKIPPED","precondition":false,"level":2},{"number":16,"description":"Then Se muestra mensaje \"Estamos procesando tu depósito\"","duration":5,"startTime":"2024-02-19T19:30:28.328287300-05:00[America/Lima]","result":"SKIPPED","precondition":false,"level":2}]}]}],"userStory":{"id":"DepositoTarjeta","storyName":"Poder generar el código de depósito","displayName":"Poder generar el código de depósito","path":"DepositoTarjeta","pathElements":[{"name":"DepositoTarjeta","description":""}],"type":"feature"},"title":"Validar que permita depositar mediante tarjeta con el monto máximo","description":"","backgroundTitle":"","backgroundDescription":"","tags":[{"name":"Chrome","type":"context","displayName":"Chrome"},{"name":"Windows","type":"context","displayName":"Windows"},{"name":"Chrome, Windows","type":"context","displayName":"Chrome, Windows"},{"name":"ValidarDepositoMontoMinimo","type":"tag","displayName":"ValidarDepositoMontoMinimo"}],"startTime":"2024-02-19T19:29:50.422408400-05:00[America/Lima]","duration":5600,"testFailureCause":{"errorType":"org.openqa.selenium.ElementClickInterceptedException","message":"element click intercepted: Element \u003cbutton id\u003d\"depositButton\" class\u003d\"jsx-bbc0a237ca44e34d clmc-btn-primary clmc-disabled\"\u003e...\u003c/button\u003e is not clickable at point (768, 607). Other element would receive the click: \u003cdiv class\u003d\"jsx-bbc0a237ca44e34d clmc-flex-center containerBtnPasarelaFlex\"\u003e...\u003c/div\u003e\n  (Session info: chrome\u003d121.0.6167.185)\nBuild info: version: \u00274.12.0\u0027, revision: \u0027249f2a7d1b*\u0027\nSystem info: os.name: \u0027Windows 10\u0027, os.arch: \u0027amd64\u0027, os.version: \u002710.0\u0027, java.version: \u002721.0.1\u0027\nDriver info: org.openqa.selenium.chrome.ChromeDriver\nCommand: [b02882735822dd6505d810ed308f9b91, clickElement {id\u003dB78C1B15E8C088EC93786EAE31AF9569_element_163}]\nCapabilities {acceptInsecureCerts: false, browserName: chrome, browserVersion: 121.0.6167.185, chrome: {chromedriverVersion: 121.0.6167.184 (057a8ae7deb..., userDataDir: C:\\Users\\RCARRA~1\\AppData\\L...}, fedcm:accounts: true, goog:chromeOptions: {debuggerAddress: localhost:55821}, networkConnectionEnabled: false, pageLoadStrategy: normal, platformName: windows, proxy: Proxy(), se:cdp: ws://localhost:55821/devtoo..., se:cdpVersion: 121.0.6167.185, setWindowRect: true, strictFileInteractability: false, timeouts: {implicit: 0, pageLoad: 300000, script: 30000}, unhandledPromptBehavior: dismiss and notify, webauthn:extension:credBlob: true, webauthn:extension:largeBlob: true, webauthn:extension:minPinLength: true, webauthn:extension:prf: true, webauthn:virtualAuthenticators: true}\nElement: [[ChromeDriver: chrome on windows (b02882735822dd6505d810ed308f9b91)] -\u003e xpath: //button[@id\u003d\u0027depositButton\u0027]]\nSession ID: b02882735822dd6505d810ed308f9b91","stackTrace":[{"declaringClass":"atlantic.main.util.PageObjectUtil","methodName":"seleniumClick","fileName":"PageObjectUtil.java","lineNumber":63},{"declaringClass":"atlantic.main.page.PageDeposito","methodName":"seleccionarBotonDepositoSiguiente","fileName":"PageDeposito.java","lineNumber":66},{"declaringClass":"net.thucydides.core.steps.BaseMethodRunner","methodName":"invokeMethod","fileName":"BaseMethodRunner.java","lineNumber":18},{"declaringClass":"net.thucydides.core.steps.NormalMethodRunner","methodName":"invokeMethodAndNotifyFailures","fileName":"NormalMethodRunner.java","lineNumber":18},{"declaringClass":"net.thucydides.core.steps.StepInterceptor","methodName":"runNormalMethod","fileName":"StepInterceptor.java","lineNumber":420},{"declaringClass":"net.thucydides.core.steps.StepInterceptor","methodName":"testStepResult","fileName":"StepInterceptor.java","lineNumber":195},{"declaringClass":"net.thucydides.core.steps.StepInterceptor","methodName":"intercept","fileName":"StepInterceptor.java","lineNumber":92},{"declaringClass":"atlantic.main.step.StepDeposito","methodName":"seleccionarDepositoSiguiente","fileName":"StepDeposito.java","lineNumber":23},{"declaringClass":"net.thucydides.core.steps.BaseMethodRunner","methodName":"invokeMethod","fileName":"BaseMethodRunner.java","lineNumber":18},{"declaringClass":"net.thucydides.core.steps.NormalMethodRunner","methodName":"invokeMethodAndNotifyFailures","fileName":"NormalMethodRunner.java","lineNumber":18},{"declaringClass":"net.thucydides.core.steps.StepInterceptor","methodName":"runNormalMethod","fileName":"StepInterceptor.java","lineNumber":420},{"declaringClass":"net.thucydides.core.steps.StepInterceptor","methodName":"testStepResult","fileName":"StepInterceptor.java","lineNumber":195},{"declaringClass":"net.thucydides.core.steps.StepInterceptor","methodName":"intercept","fileName":"StepInterceptor.java","lineNumber":92},{"declaringClass":"com.atlantic.test.definition.DefDepositoTarjeta","methodName":"selecciono_botón_siguiente_tarjeta","fileName":"DefDepositoTarjeta.java","lineNumber":32},{"declaringClass":"io.cucumber.java.Invoker","methodName":"doInvoke","fileName":"Invoker.java","lineNumber":66},{"declaringClass":"io.cucumber.java.Invoker","methodName":"invoke","fileName":"Invoker.java","lineNumber":24},{"declaringClass":"io.cucumber.java.AbstractGlueDefinition","methodName":"invokeMethod","fileName":"AbstractGlueDefinition.java","lineNumber":47},{"declaringClass":"io.cucumber.java.JavaStepDefinition","methodName":"execute","fileName":"JavaStepDefinition.java","lineNumber":29},{"declaringClass":"io.cucumber.core.runner.CoreStepDefinition","methodName":"execute","fileName":"CoreStepDefinition.java","lineNumber":66},{"declaringClass":"io.cucumber.core.runner.PickleStepDefinitionMatch","methodName":"runStep","fileName":"PickleStepDefinitionMatch.java","lineNumber":63},{"declaringClass":"io.cucumber.core.runner.TestStep","methodName":"executeStep","fileName":"TestStep.java","lineNumber":84},{"declaringClass":"io.cucumber.core.runner.TestStep","methodName":"run","fileName":"TestStep.java","lineNumber":56},{"declaringClass":"io.cucumber.core.runner.PickleStepTestStep","methodName":"run","fileName":"PickleStepTestStep.java","lineNumber":51},{"declaringClass":"io.cucumber.core.runner.TestCase","methodName":"run","fileName":"TestCase.java","lineNumber":84},{"declaringClass":"io.cucumber.core.runner.Runner","methodName":"runPickle","fileName":"Runner.java","lineNumber":75},{"declaringClass":"io.cucumber.core.runtime.CucumberExecutionContext","methodName":"lambda$runTestCase$5","fileName":"CucumberExecutionContext.java","lineNumber":137},{"declaringClass":"io.cucumber.core.runtime.RethrowingThrowableCollector","methodName":"executeAndThrow","fileName":"RethrowingThrowableCollector.java","lineNumber":23},{"declaringClass":"io.cucumber.core.runtime.CucumberExecutionContext","methodName":"runTestCase","fileName":"CucumberExecutionContext.java","lineNumber":137},{"declaringClass":"io.cucumber.junit.FeatureRunner","methodName":"runChild","fileName":"FeatureRunner.java","lineNumber":144},{"declaringClass":"io.cucumber.junit.FeatureRunner","methodName":"runChild","fileName":"FeatureRunner.java","lineNumber":28},{"declaringClass":"io.cucumber.junit.FeatureRunner","methodName":"run","fileName":"FeatureRunner.java","lineNumber":137},{"declaringClass":"io.cucumber.junit.CucumberSerenityBaseRunner","methodName":"runChild","fileName":"CucumberSerenityBaseRunner.java","lineNumber":330},{"declaringClass":"io.cucumber.junit.CucumberSerenityBaseRunner","methodName":"runChild","fileName":"CucumberSerenityBaseRunner.java","lineNumber":51},{"declaringClass":"com.atlantic.test.runner.RunPersonalizar","methodName":"run","fileName":"RunPersonalizar.java","lineNumber":36}]},"testFailureClassname":"org.openqa.selenium.ElementClickInterceptedException","testFailureMessage":"element click intercepted: Element \u003cbutton id\u003d\"depositButton\" class\u003d\"jsx-bbc0a237ca44e34d clmc-btn-primary clmc-disabled\"\u003e...\u003c/button\u003e is not clickable at point (768, 607). Other element would receive the click: \u003cdiv class\u003d\"jsx-bbc0a237ca44e34d clmc-flex-center containerBtnPasarelaFlex\"\u003e...\u003c/div\u003e\n  (Session info: chrome\u003d121.0.6167.185)\nBuild info: version: \u00274.12.0\u0027, revision: \u0027249f2a7d1b*\u0027\nSystem info: os.name: \u0027Windows 10\u0027, os.arch: \u0027amd64\u0027, os.version: \u002710.0\u0027, java.version: \u002721.0.1\u0027\nDriver info: org.openqa.selenium.chrome.ChromeDriver\nCommand: [b02882735822dd6505d810ed308f9b91, clickElement {id\u003dB78C1B15E8C088EC93786EAE31AF9569_element_163}]\nCapabilities {acceptInsecureCerts: false, browserName: chrome, browserVersion: 121.0.6167.185, chrome: {chromedriverVersion: 121.0.6167.184 (057a8ae7deb..., userDataDir: C:\\Users\\RCARRA~1\\AppData\\L...}, fedcm:accounts: true, goog:chromeOptions: {debuggerAddress: localhost:55821}, networkConnectionEnabled: false, pageLoadStrategy: normal, platformName: windows, proxy: Proxy(), se:cdp: ws://localhost:55821/devtoo..., se:cdpVersion: 121.0.6167.185, setWindowRect: true, strictFileInteractability: false, timeouts: {implicit: 0, pageLoad: 300000, script: 30000}, unhandledPromptBehavior: dismiss and notify, webauthn:extension:credBlob: true, webauthn:extension:largeBlob: true, webauthn:extension:minPinLength: true, webauthn:extension:prf: true, webauthn:virtualAuthenticators: true}\nElement: [[ChromeDriver: chrome on windows (b02882735822dd6505d810ed308f9b91)] -\u003e xpath: //button[@id\u003d\u0027depositButton\u0027]]\nSession ID: b02882735822dd6505d810ed308f9b91","testFailureSummary":"ERROR;org.openqa.selenium.ElementClickInterceptedException;element click intercepted: Element \u003cbutton id\u003d\"depositButton\" class\u003d\"jsx-bbc0a237ca44e34d clmc-btn-primary clmc-disabled\"\u003e...\u003c/button\u003e is not clickable at point (768, 607). Other element would receive the click: \u003cdiv class\u003d\"jsx-bbc0a237ca44e34d clmc-flex-center containerBtnPasarelaFlex\"\u003e...\u003c/div\u003e\n  (Session info: chrome\u003d121.0.6167.185)\nBuild info: version: \u00274.12.0\u0027, revision: \u0027249f2a7d1b*\u0027\nSystem info: os.name: \u0027Windows 10\u0027, os.arch: \u0027amd64\u0027, os.version: \u002710.0\u0027, java.version: \u002721.0.1\u0027\nDriver info: org.openqa.selenium.chrome.ChromeDriver\nCommand: [b02882735822dd6505d810ed308f9b91, clickElement {id\u003dB78C1B15E8C088EC93786EAE31AF9569_element_163}]\nCapabilities {acceptInsecureCerts: false, browserName: chrome, browserVersion: 121.0.6167.185, chrome: {chromedriverVersion: 121.0.6167.184 (057a8ae7deb..., userDataDir: C:\\Users\\RCARRA~1\\AppData\\L...}, fedcm:accounts: true, goog:chromeOptions: {debuggerAddress: localhost:55821}, networkConnectionEnabled: false, pageLoadStrategy: normal, platformName: windows, proxy: Proxy(), se:cdp: ws://localhost:55821/devtoo..., se:cdpVersion: 121.0.6167.185, setWindowRect: true, strictFileInteractability: false, timeouts: {implicit: 0, pageLoad: 300000, script: 30000}, unhandledPromptBehavior: dismiss and notify, webauthn:extension:credBlob: true, webauthn:extension:largeBlob: true, webauthn:extension:minPinLength: true, webauthn:extension:prf: true, webauthn:virtualAuthenticators: true}\nElement: [[ChromeDriver: chrome on windows (b02882735822dd6505d810ed308f9b91)] -\u003e xpath: //button[@id\u003d\u0027depositButton\u0027]]\nSession ID: b02882735822dd6505d810ed308f9b91;PageObjectUtil.java","projectKey":"","annotatedResult":"ERROR","driver":"chrome","isManualTestingUpToDate":false,"context":"chrome,windows","dataTable":{"headers":["Vertical","Pasarela","Tarjeta","Fechacaducidad","CVV"],"rows":[{"values":["Ir a casino","DebitoCredito","4009175332806176","11/25","123"],"lineNumber":26,"result":"ERROR"}],"predefinedRows":true,"scenarioOutline":"When Me encuentro en \"\u003cVertical\u003e\"\n\rAnd ingreso los datos del usuario\n\rAnd Selecciono botón Depositar\"\n\rAnd Selecciono \"\u003cPasarela\u003e\"\n\rAnd Selecciono el monto:\n\rAnd Acepto términos y condiciones de depósito\n\rAnd Selecciono botón Siguiente tarjeta\n\rAnd Selecciono boton Pagar sin agregar tarjeta\n\rAnd Ingreso \"\u003cTarjeta\u003e\" \"\u003cFechacaducidad\u003e\" Ingreso \"\u003cCVV\u003e\"\n\rAnd Selcciono botón Depositar\n\rThen Se muestra mensaje \"Estamos procesando tu depósito\"\n\r","dataSetDescriptors":[{"startRow":0,"rowCount":0,"name":"","description":""}]},"manual":false,"testSource":"Cucumber","order":0,"result":"ERROR","scenarioOutline":"When Me encuentro en \"\u003cVertical\u003e\"\r\nAnd ingreso los datos del usuario\r\n|usuario | contrasenna|\r\n|usuVahpc | atl1Vipeh|\r\nAnd Selecciono botón Depositar\"\r\nAnd Selecciono \"\u003cPasarela\u003e\"\r\nAnd Selecciono el monto:\r\n|MontoOrigen|\r\n|300|\r\nAnd Acepto términos y condiciones de depósito\r\nAnd Selecciono botón Siguiente tarjeta\r\nAnd Selecciono boton Pagar sin agregar tarjeta\r\nAnd Ingreso \"\u003cTarjeta\u003e\" \"\u003cFechacaducidad\u003e\" Ingreso \"\u003cCVV\u003e\"\r\nAnd Selcciono botón Depositar\r\nThen Se muestra mensaje \"Estamos procesando tu depósito\""}